dingding/__init__.py
dingding/dingding.py
dingding-0.6.2.dist-info/LICENSE
dingding-0.6.2.dist-info/METADATA
dingding-0.6.2.dist-info/WHEEL
dingding-0.6.2.dist-info/top_level.txt
dingding-0.6.2.dist-info/RECORD
