Metadata-Version: 2.1
Name: dingding
Version: 0.6.2
Summary: ding ding robot
Home-page: https://github.com/Twotiger/dingding
Author: Twotiger
Author-email: dgl0518@gmail.com
License: UNKNOWN
Platform: UNKNOWN
Classifier: Programming Language :: Python :: 3
Classifier: License :: OSI Approved :: MIT License
Classifier: Operating System :: OS Independent
